pl_bolts/__about__.py
pl_bolts/__init__.py
pl_bolts/callbacks/__init__.py
pl_bolts/callbacks/byol_updates.py
pl_bolts/callbacks/data_monitor.py
pl_bolts/callbacks/knn_online.py
pl_bolts/callbacks/printing.py
pl_bolts/callbacks/sparseml.py
pl_bolts/callbacks/ssl_online.py
pl_bolts/callbacks/torch_ort.py
pl_bolts/callbacks/variational.py
pl_bolts/callbacks/verification/__init__.py
pl_bolts/callbacks/verification/base.py
pl_bolts/callbacks/verification/batch_gradient.py
pl_bolts/callbacks/vision/__init__.py
pl_bolts/callbacks/vision/confused_logit.py
pl_bolts/callbacks/vision/image_generation.py
pl_bolts/callbacks/vision/sr_image_logger.py
pl_bolts/datamodules/__init__.py
pl_bolts/datamodules/async_dataloader.py
pl_bolts/datamodules/binary_emnist_datamodule.py
pl_bolts/datamodules/binary_mnist_datamodule.py
pl_bolts/datamodules/cifar10_datamodule.py
pl_bolts/datamodules/cityscapes_datamodule.py
pl_bolts/datamodules/emnist_datamodule.py
pl_bolts/datamodules/experience_source.py
pl_bolts/datamodules/fashion_mnist_datamodule.py
pl_bolts/datamodules/imagenet_datamodule.py
pl_bolts/datamodules/kitti_datamodule.py
pl_bolts/datamodules/mnist_datamodule.py
pl_bolts/datamodules/sklearn_datamodule.py
pl_bolts/datamodules/sr_datamodule.py
pl_bolts/datamodules/ssl_imagenet_datamodule.py
pl_bolts/datamodules/stl10_datamodule.py
pl_bolts/datamodules/vision_datamodule.py
pl_bolts/datamodules/vocdetection_datamodule.py
pl_bolts/datasets/__init__.py
pl_bolts/datasets/array_dataset.py
pl_bolts/datasets/base_dataset.py
pl_bolts/datasets/cifar10_dataset.py
pl_bolts/datasets/concat_dataset.py
pl_bolts/datasets/dummy_dataset.py
pl_bolts/datasets/emnist_dataset.py
pl_bolts/datasets/imagenet_dataset.py
pl_bolts/datasets/kitti_dataset.py
pl_bolts/datasets/mnist_dataset.py
pl_bolts/datasets/sr_celeba_dataset.py
pl_bolts/datasets/sr_dataset_mixin.py
pl_bolts/datasets/sr_mnist_dataset.py
pl_bolts/datasets/sr_stl10_dataset.py
pl_bolts/datasets/ssl_amdim_datasets.py
pl_bolts/datasets/utils.py
lightning_bolts-0.7.0.dist-info/LICENSE
lightning_bolts-0.7.0.dist-info/METADATA
lightning_bolts-0.7.0.dist-info/WHEEL
lightning_bolts-0.7.0.dist-info/top_level.txt
lightning_bolts-0.7.0.dist-info/RECORD
