Metadata-Version: 2.1
Name: lightning-bolts
Version: 0.7.0
Summary: Lightning Bolts is a community contribution for ML researchers.
Home-page: https://github.com/Lightning-AI/lightning-bolts
Download-URL: https://github.com/PyTorchLightning/lightning-bolts
Author: Lightning AI et al.
Author-email: pytorch@lightning.ai
License: Apache-2.0
Project-URL: Bug Tracker, https://github.com/PyTorchLightning/lightning-bolts/issues
Project-URL: Documentation, https://lightning-bolts.rtfd.io/en/latest/
Project-URL: Source Code, https://github.com/PyTorchLightning/lightning-bolts
Keywords: deep learning,pytorch,AI
Classifier: Environment :: Console
Classifier: Natural Language :: English
Classifier: Development Status :: 4 - Beta
Classifier: Intended Audience :: Developers
Classifier: Topic :: Scientific/Engineering :: Artificial Intelligence
Classifier: Topic :: Scientific/Engineering :: Image Recognition
Classifier: Topic :: Scientific/Engineering :: Information Analysis
Classifier: License :: OSI Approved :: Apache Software License
Classifier: Operating System :: OS Independent
Classifier: Programming Language :: Python :: 3
Classifier: Programming Language :: Python :: 3.8
Classifier: Programming Language :: Python :: 3.9
Classifier: Programming Language :: Python :: 3.10
Requires-Python: >=3.8
License-File: LICENSE
Requires-Dist: numpy
Requires-Dist: pytorch-lightning (<2.0.0,>1.7.0)
Requires-Dist: torchmetrics
Requires-Dist: lightning-utilities (>0.3.1)
Requires-Dist: torchvision (>=0.10.0)
Requires-Dist: tensorboard (>=2.9.1)
Provides-Extra: dev
Requires-Dist: torchvision (>=0.10.0) ; extra == 'dev'
Requires-Dist: scikit-learn (>=1.0.2) ; extra == 'dev'
Requires-Dist: Pillow (>9.0.0) ; extra == 'dev'
Requires-Dist: gym[atari] (<0.22.0,>=0.17.2) ; extra == 'dev'
Requires-Dist: atari-py (!=0.2.6,<0.3,>0.2) ; extra == 'dev'
Requires-Dist: box2d-py (<2.4,>2.3) ; extra == 'dev'
Requires-Dist: opencv-python-headless (>=4.5.5.62) ; extra == 'dev'
Requires-Dist: matplotlib (>3.0.0) ; extra == 'dev'
Requires-Dist: wandb (>0.13.0) ; extra == 'dev'
Requires-Dist: scipy (>1.5.0) ; extra == 'dev'
Requires-Dist: coverage[toml] (>7.0.0) ; extra == 'dev'
Requires-Dist: pytest (==7.4.0) ; extra == 'dev'
Requires-Dist: pytest-cov (==4.1.0) ; extra == 'dev'
Requires-Dist: pytest-timeout (==2.1.0) ; extra == 'dev'
Requires-Dist: pytest-rerunfailures (==11.1.2) ; extra == 'dev'
Requires-Dist: sparseml (>1.0.0) ; extra == 'dev'
Requires-Dist: ale-py (>=0.7) ; extra == 'dev'
Requires-Dist: jsonargparse[signatures] (>4.0.0) ; extra == 'dev'
Provides-Extra: extra
Requires-Dist: torchvision (>=0.10.0) ; extra == 'extra'
Requires-Dist: scikit-learn (>=1.0.2) ; extra == 'extra'
Requires-Dist: Pillow (>9.0.0) ; extra == 'extra'
Requires-Dist: gym[atari] (<0.22.0,>=0.17.2) ; extra == 'extra'
Requires-Dist: atari-py (!=0.2.6,<0.3,>0.2) ; extra == 'extra'
Requires-Dist: box2d-py (<2.4,>2.3) ; extra == 'extra'
Requires-Dist: opencv-python-headless (>=4.5.5.62) ; extra == 'extra'
Requires-Dist: matplotlib (>3.0.0) ; extra == 'extra'
Requires-Dist: wandb (>0.13.0) ; extra == 'extra'
Requires-Dist: scipy (>1.5.0) ; extra == 'extra'
Provides-Extra: loggers
Requires-Dist: matplotlib (>3.0.0) ; extra == 'loggers'
Requires-Dist: wandb (>0.13.0) ; extra == 'loggers'
Requires-Dist: scipy (>1.5.0) ; extra == 'loggers'
Provides-Extra: models
Requires-Dist: torchvision (>=0.10.0) ; extra == 'models'
Requires-Dist: scikit-learn (>=1.0.2) ; extra == 'models'
Requires-Dist: Pillow (>9.0.0) ; extra == 'models'
Requires-Dist: gym[atari] (<0.22.0,>=0.17.2) ; extra == 'models'
Requires-Dist: atari-py (!=0.2.6,<0.3,>0.2) ; extra == 'models'
Requires-Dist: box2d-py (<2.4,>2.3) ; extra == 'models'
Requires-Dist: opencv-python-headless (>=4.5.5.62) ; extra == 'models'
Provides-Extra: test
Requires-Dist: coverage[toml] (>7.0.0) ; extra == 'test'
Requires-Dist: pytest (==7.4.0) ; extra == 'test'
Requires-Dist: pytest-cov (==4.1.0) ; extra == 'test'
Requires-Dist: pytest-timeout (==2.1.0) ; extra == 'test'
Requires-Dist: pytest-rerunfailures (==11.1.2) ; extra == 'test'
Requires-Dist: scikit-learn (>=1.0.2) ; extra == 'test'
Requires-Dist: sparseml (>1.0.0) ; extra == 'test'
Requires-Dist: ale-py (>=0.7) ; extra == 'test'
Requires-Dist: jsonargparse[signatures] (>4.0.0) ; extra == 'test'
Provides-Extra: typing
Requires-Dist: mypy (==1.3.0) ; extra == 'typing'
